openrover.py
openrover-1.0.0.dist-info/WHEEL
openrover-1.0.0.dist-info/METADATA
openrover-1.0.0.dist-info/RECORD
