Metadata-Version: 2.1
Name: openrover
Version: 1.0.0
Summary: Please use the roverpro package instead
Home-page: https://github.com/RoverRobotics/roverpro-python
License: BSD-3-Clause
Author: Dan Rose
Author-email: dan@digilabs.io
Maintainer: Dan Rose
Maintainer-email: dan@digilabs.io
Requires-Python: >=3.6,<4.0
Classifier: License :: OSI Approved :: BSD License
Classifier: Programming Language :: Python :: 3
Classifier: Programming Language :: Python :: 3.6
Classifier: Programming Language :: Python :: 3.7
Classifier: Programming Language :: Python :: 3.8
Requires-Dist: roverpro
Project-URL: Repository, https://github.com/RoverRobotics/roverpro-python
